Metadata-Version: 2.1
Name: data-analysis-tools-jms
Version: 0.0.1
Summary: A data processor package
Home-page: https://github.com/Jane-Dream/data-analysis-tools
Author: Jane-Dream
Author-email: janedream515@gmail.com
Classifier: Programming Language :: Python :: 3
Classifier: License :: OSI Approved :: MIT License
Classifier: Operating System :: OS Independent
Requires-Python: >=3.6
License-File: LICENSE
Requires-Dist: requests >=2.24.0
Requires-Dist: jieba >=0.42.1
Requires-Dist: setuptools >=42
